fkb/__init__.py
fkb/__main__.py
fkb/cl_parser.py
fkb/config.py
fkb/database.py
fkb/filesystem.py
fkb/initialize.py
fkb/main.py
fkb/object.py
fkb/commands/add.py
fkb/commands/config.py
fkb/commands/delete.py
fkb/commands/erase.py
fkb/commands/grep.py
fkb/commands/search.py
fkb/commands/update.py
fkb/commands/watch.py
fkb/commands/backup/export.py
fkb/commands/backup/ingest.py
fkb/commands/note/catnote.py
fkb/commands/note/deletenote.py
fkb/commands/note/editnote.py
fkb/printer/grep.py
fkb/printer/search.py
fkb/printer/style.py
filekb-0.1.1.dist-info/METADATA
filekb-0.1.1.dist-info/WHEEL
filekb-0.1.1.dist-info/entry_points.txt
filekb-0.1.1.dist-info/licenses/LICENSE
filekb-0.1.1.dist-info/RECORD
