Metadata-Version: 2.1
Name: filekb
Version: 0.1.1
Summary: A knowledge base with file tracking and document note integration
Author: ArktisDev
License-File: LICENSE
Classifier: Operating System :: OS Independent
Classifier: Programming Language :: Python :: 3
Requires-Python: >=3.7
